lib_resume_builder_AIHawk/__init__.py
lib_resume_builder_AIHawk/config.py
lib_resume_builder_AIHawk/gpt_resume.py
lib_resume_builder_AIHawk/gpt_resume_job_description.py
lib_resume_builder_AIHawk/manager_facade.py
lib_resume_builder_AIHawk/module_loader.py
lib_resume_builder_AIHawk/resume.py
lib_resume_builder_AIHawk/resume_generator.py
lib_resume_builder_AIHawk/style_manager.py
lib_resume_builder_AIHawk/utils.py
lib_resume_builder_AIHawk/resume_job_description_prompt/__init__.py
lib_resume_builder_AIHawk/resume_job_description_prompt/strings_feder-cr.py
lib_resume_builder_AIHawk/resume_prompt/__init__.py
lib_resume_builder_AIHawk/resume_prompt/strings_feder-cr.py
lib_resume_builder_AIHawk/resume_style/__init__.py
lib_resume_builder_AIHawk/resume_style/style_krishnavalliappan.css
lib_resume_builder_AIHawk-0.2.dist-info/LICENSE
lib_resume_builder_AIHawk-0.2.dist-info/METADATA
lib_resume_builder_AIHawk-0.2.dist-info/WHEEL
lib_resume_builder_AIHawk-0.2.dist-info/top_level.txt
lib_resume_builder_AIHawk-0.2.dist-info/RECORD
