Metadata-Version: 2.1
Name: lib_resume_builder_AIHawk
Version: 0.2
Summary: A package to generate AI-assisted resumes using GPT models
Home-page: https://github.com/feder-cr/lib_resume_builder_AIHawk
Author: feder-cr
Author-email: federico.elia.majo@gmail.com
Classifier: Programming Language :: Python :: 3
Classifier: License :: OSI Approved :: MIT License
Classifier: Operating System :: OS Independent
Requires-Python: >=3.10
License-File: LICENSE
Requires-Dist: langchain
Requires-Dist: langchain-community
Requires-Dist: langchain-core
Requires-Dist: langchain-openai
Requires-Dist: langchain-text-splitters
Requires-Dist: langsmith
Requires-Dist: openai
Requires-Dist: regex==2024.7.24
Requires-Dist: selenium==4.9.1
Requires-Dist: webdriver-manager==4.0.2
Requires-Dist: inquirer
Requires-Dist: faiss-cpu
